spine/__init__.py
spine/blendmode.py
spine/bone.pxd
spine/bone.pyd
spine/event.py
spine/ikconstraint.pxd
spine/ikconstraint.pyd
spine/skin.py
spine/slot.pxd
spine/slot.pyd
spine/spineevent.pxd
spine/spineevent.pyd
spine/utils.pxd
spine/utils.pyd
spine/animation/__init__.py
spine/animation/animation.pxd
spine/animation/animation.pyd
spine/animation/animationstate.pxd
spine/animation/animationstate.pyd
spine/animation/animationstatedata.py
spine/animation/attachmenttimeline.pxd
spine/animation/attachmenttimeline.pyd
spine/animation/colortimeline.pxd
spine/animation/colortimeline.pyd
spine/animation/curvetimeline.pxd
spine/animation/curvetimeline.pyd
spine/animation/drawordertimeline.pxd
spine/animation/drawordertimeline.pyd
spine/animation/eventtimeline.pxd
spine/animation/eventtimeline.pyd
spine/animation/ffdtimeline.pxd
spine/animation/ffdtimeline.pyd
spine/animation/flipxtimeline.pxd
spine/animation/flipxtimeline.pyd
spine/animation/flipytimeline.pxd
spine/animation/flipytimeline.pyd
spine/animation/ikconstrainttimeline.pxd
spine/animation/ikconstrainttimeline.pyd
spine/animation/rotatetimeline.pxd
spine/animation/rotatetimeline.pyd
spine/animation/scaletimeline.pxd
spine/animation/scaletimeline.pyd
spine/animation/timeline.pxd
spine/animation/timeline.pyd
spine/animation/trackentry.pxd
spine/animation/trackentry.pyd
spine/animation/translatetimeline.pxd
spine/animation/translatetimeline.pyd
spine/atlas/__init__.py
spine/atlas/atlas.py
spine/atlas/atlaspage.py
spine/atlas/atlasreader.py
spine/atlas/atlasregion.py
spine/atlas/texture.py
spine/attachment/__init__.py
spine/attachment/atlasattachmentloader.py
spine/attachment/attachment.pxd
spine/attachment/attachment.pyd
spine/attachment/boundingboxattachment.pxd
spine/attachment/boundingboxattachment.pyd
spine/attachment/meshattachment.pxd
spine/attachment/meshattachment.pyd
spine/attachment/regionattachment.pxd
spine/attachment/regionattachment.pyd
spine_cython-0.5.1.dist-info/DESCRIPTION.rst
spine_cython-0.5.1.dist-info/METADATA
spine_cython-0.5.1.dist-info/RECORD
spine_cython-0.5.1.dist-info/WHEEL
spine_cython-0.5.1.dist-info/metadata.json
spine_cython-0.5.1.dist-info/top_level.txt
