Metadata-Version: 2.0
Name: spine-cython
Version: 0.5.1
Summary: Spine runtimes for python.
Home-page: UNKNOWN
Author: Tileworks Games and other contributors.
Author-email: tileworksgames@gmail.com
License: Spine Runtimes Software License
Keywords: spine
Platform: UNKNOWN
Classifier: Intended Audience :: Developers
Classifier: Intended Audience :: End Users/Desktop
Classifier: Intended Audience :: Information Technology
Classifier: Programming Language :: Python :: 2.7
Classifier: Operating System :: Microsoft :: Windows
Classifier: Topic :: Games/Entertainment
Classifier: Topic :: Multimedia :: Graphics
